spc_export/__init__.py
spc_export/__main__.py
spc_export/spc.py
spc_export/spcexport.py
spc_export-1.0.1.dist-info/METADATA
spc_export-1.0.1.dist-info/WHEEL
spc_export-1.0.1.dist-info/entry_points.txt
spc_export-1.0.1.dist-info/top_level.txt
spc_export-1.0.1.dist-info/RECORD
