Metadata-Version: 2.1
Name: spc-export
Version: 1.0.1
Summary: SPC-Export is a tool designed to facilitate the conversion of SPC from Brama measurements into a format that is both human- and Python-readable. This streamlined conversion ensures easy access, readability, and visualization of measurement data for further analysis and interpretation.
Home-page: https://gitlab.tuwien.ac.at/iap/aip/anp/spc-export
Author: Richard van Nieuwenhoven, Markus Valtiner
Author-email: richard.nieuwenhoven@tuwien.ac.at, markus.valtiner@tuwien.ac.at
Project-URL: Homepage, https://gitlab.tuwien.ac.at/iap/aip/anp/spc-export
Keywords: spc conversion
Classifier: Programming Language :: Python :: 3
Classifier: License :: OSI Approved :: MIT License
Classifier: Operating System :: OS Independent
Requires-Python: >=3.1
Requires-Dist: matplotlib>=3.5.1
Requires-Dist: NumPy<2.0
